balancerv2cad/BalancerConstants.py
balancerv2cad/StableMath.py
balancerv2cad/StablePool.py
balancerv2cad/WeightedMath.py
balancerv2cad/WeightedPool.py
balancerv2cad/__init__.py
balancerv2cad/logger/__init__.py
balancerv2cad/logger/pkg_logger.py
balancerv2cad/main.py
balancerv2cad/util.py
balancerv2cad-0.1.93.dist-info/entry_points.txt
balancerv2cad-0.1.93.dist-info/LICENSE
balancerv2cad-0.1.93.dist-info/WHEEL
balancerv2cad-0.1.93.dist-info/METADATA
balancerv2cad-0.1.93.dist-info/RECORD
