Metadata-Version: 2.1
Name: balancerv2cad
Version: 0.1.93
Summary: A preconfigured Python package, using python poetry
Home-page: https://github.com/officialnico/balancerv2cad.git
License: MIT
Author: Nico Rodriguez, Thomas Liu, Marcin Jaczynski
Requires-Python: >=3.8,<4.0
Classifier: License :: OSI Approved :: MIT License
Classifier: Programming Language :: Python :: 3
Classifier: Programming Language :: Python :: 3.8
Classifier: Programming Language :: Python :: 3.9
Project-URL: Repository, https://github.com/officialnico/balancerv2cad.git
